{
	"info": {
		"_postman_id": "5651eb6a-eee8-4f4d-ba80-c5412fd85705",
		"name": "AgileActors",
		"schema": "https://schema.getpostman.com/json/collection/v2.1.0/collection.json",
		"_exporter_id": "88478"
	},
	"item": [
		{
			"name": "Create Transaction",
			"request": {
				"method": "POST",
				"header": [],
				"url": {
					"raw": "http://localhost:8080/transaction?sourceAccountId=account1&targetAccountId=account2&amount=10000&currency",
					"protocol": "http",
					"host": [
						"localhost"
					],
					"port": "8080",
					"path": [
						"transaction"
					],
					"query": [
						{
							"key": "sourceAccountId",
							"value": "account1"
						},
						{
							"key": "targetAccountId",
							"value": "account2"
						},
						{
							"key": "amount",
							"value": "10000"
						},
						{
							"key": "currency",
							"value": null
						}
					]
				}
			},
			"response": []
		},
		{
			"name": "List Accounts",
			"request": {
				"method": "GET",
				"header": [],
				"url": {
					"raw": "http://localhost:8080/accounts",
					"protocol": "http",
					"host": [
						"localhost"
					],
					"port": "8080",
					"path": [
						"accounts"
					]
				}
			},
			"response": []
		},
		{
			"name": "List Transactions",
			"request": {
				"method": "GET",
				"header": [],
				"url": {
					"raw": "http://localhost:8080/transactions",
					"protocol": "http",
					"host": [
						"localhost"
					],
					"port": "8080",
					"path": [
						"transactions"
					]
				}
			},
			"response": []
		}
	]
}